<!DOCTYPE ui:UiBinder SYSTEM "http://dl.google.com/gwt/DTD/xhtml.ent">
<ui:UiBinder xmlns:ui="urn:ui:com.google.gwt.uibinder"
	xmlns:g="urn:import:com.google.gwt.user.client.ui">
	
	
	<div ui:field="ElementoNelCarrello">
	 <style is='custom-style'>
	 .RimuoviDalCarrello{
		 background-color: rgba(229, 57, 53, 1);
		 color:white;
		}
	.incrementa{
		background-color: rgba(139, 195, 74, 1);
	}
	.decrementa{
				 background-color: rgba(229, 57, 53, 1);
		 color:white;
	}
	.prodottiElemento{
	
	}
	.border{
	padding-right:20px;
	
	}
	.inline{
	display: inline;
	}
	 </style>
	
	
	<table >
		<tr>
				<td class="border" align="left"><paper-button class="RimuoviDalCarrello" ui:field="RimuoviRicetta">Rimuovi</paper-button></td>
				<td class="border" align="left">
					<div class="inline">Quantità:</div>
					<div class="inline" ui:field="quantita">1</div>
				</td>
				<td class="border" align="left">
						<paper-button class="incrementa" ui:field="incrementapiu" >+1</paper-button>
						<paper-button class="decrementa" ui:field="incrementameno">-1</paper-button>
				</td>
				<td class="border" align="left" ui:field="nome"></td>
				<td class="border" align="left"> 
						<paper-dropdown-menu label="Prodotti Scelti" class="prodottiElemento">
						  <paper-menu class="dropdown-content" ui:field="ProdottoItem">
						  </paper-menu>
						</paper-dropdown-menu>
				</td>
				<td class="border" align="left" ui:field="costo"></td>
		</tr>
	</table>
	
	</div>
	


		
	
</ui:UiBinder> 